name2date/__init__.py
name2date/__main__.py
name2date/cli.py
name2date/core.py
name2date-0.1.0.dist-info/licenses/LICENSE
tests/__init__.py
tests/test_parse_filename.py
tests/test_update_file_modification_time.py
name2date-0.1.0.dist-info/METADATA
name2date-0.1.0.dist-info/WHEEL
name2date-0.1.0.dist-info/entry_points.txt
name2date-0.1.0.dist-info/top_level.txt
name2date-0.1.0.dist-info/RECORD
