Metadata-Version: 2.4
Name: name2date
Version: 0.1.0
Summary: Update Google Pixel video/photo modification dates based on their filenames
Home-page: https://github.com/kochaika/name2date
Author: Konstantin Chaika
Author-email: pro100kot14@gmail.com
Project-URL: Bug Reports, https://github.com/kochaika/name2date/issues
Project-URL: Source, https://github.com/kochaika/name2date
Keywords: video,image,date,time,metadata,file,modification,google pixel
Classifier: Development Status :: 4 - Beta
Classifier: Intended Audience :: End Users/Desktop
Classifier: License :: OSI Approved :: MIT License
Classifier: Programming Language :: Python :: 3
Classifier: Programming Language :: Python :: 3.6
Classifier: Programming Language :: Python :: 3.7
Classifier: Programming Language :: Python :: 3.8
Classifier: Programming Language :: Python :: 3.9
Classifier: Programming Language :: Python :: 3.10
Classifier: Programming Language :: Python :: 3.11
Classifier: Programming Language :: Python :: 3.12
Classifier: Topic :: Multimedia :: Video
Classifier: Topic :: Utilities
Requires-Python: >=3.6
License-File: LICENSE
Dynamic: author
Dynamic: author-email
Dynamic: classifier
Dynamic: description
Dynamic: description-content-type
Dynamic: home-page
Dynamic: keywords
Dynamic: license-file
Dynamic: project-url
Dynamic: requires-python
Dynamic: summary
